pymodaq_plugins/VERSION
pymodaq_plugins/__init__.py
pymodaq_plugins/daq_move_plugins/__init__.py
pymodaq_plugins/daq_move_plugins/daq_move_Mock.py
pymodaq_plugins/daq_move_plugins/daq_move_MockCamera.py
pymodaq_plugins/daq_move_plugins/daq_move_MockTau.py
pymodaq_plugins/daq_move_plugins/daq_move_TCPServer.py
pymodaq_plugins/daq_viewer_plugins/__init__.py
pymodaq_plugins/daq_viewer_plugins/plugins_0D/__init__.py
pymodaq_plugins/daq_viewer_plugins/plugins_0D/daq_0Dviewer_Mock.py
pymodaq_plugins/daq_viewer_plugins/plugins_0D/daq_0Dviewer_MockAdaptive.py
pymodaq_plugins/daq_viewer_plugins/plugins_0D/daq_0Dviewer_TCPServer.py
pymodaq_plugins/daq_viewer_plugins/plugins_1D/__init__.py
pymodaq_plugins/daq_viewer_plugins/plugins_1D/daq_1Dviewer_Mock.py
pymodaq_plugins/daq_viewer_plugins/plugins_1D/daq_1Dviewer_Mock_spectro.py
pymodaq_plugins/daq_viewer_plugins/plugins_1D/daq_1Dviewer_TCPServer.py
pymodaq_plugins/daq_viewer_plugins/plugins_2D/__init__.py
pymodaq_plugins/daq_viewer_plugins/plugins_2D/daq_2Dviewer_Mock.py
pymodaq_plugins/daq_viewer_plugins/plugins_2D/daq_2Dviewer_MockCamera.py
pymodaq_plugins/daq_viewer_plugins/plugins_2D/daq_2Dviewer_TCPServer.py
pymodaq_plugins/daq_viewer_plugins/plugins_ND/__init__.py
pymodaq_plugins/daq_viewer_plugins/plugins_ND/daq_NDviewer_Mock.py
pymodaq_plugins/hardware/CNRS_degrade.png
pymodaq_plugins/hardware/__init__.py
pymodaq_plugins/hardware/camera_wrapper.py
pymodaq_plugins/hardware/wrapper.py
pymodaq_plugins/models/PIDModelBeamSteering.py
pymodaq_plugins/models/__init__.py
pymodaq_plugins-3.5.0.dist-info/LICENSE
pymodaq_plugins-3.5.0.dist-info/METADATA
pymodaq_plugins-3.5.0.dist-info/WHEEL
pymodaq_plugins-3.5.0.dist-info/entry_points.txt
pymodaq_plugins-3.5.0.dist-info/top_level.txt
pymodaq_plugins-3.5.0.dist-info/RECORD
