Metadata-Version: 2.1
Name: pymodaq-plugins
Version: 3.5.0
Summary: Set of base PyMoDAQ plugins including Mock ones for development
Home-page: https://github.com/PyMoDAQ/pymodaq_plugins
Author: Sébastien Weber
Author-email: sebastien.weber@cemes.fr
License: CECILL B
Classifier: Programming Language :: Python :: 3
Classifier: Development Status :: 5 - Production/Stable
Classifier: Environment :: Other Environment
Classifier: Intended Audience :: Science/Research
Classifier: Topic :: Scientific/Engineering :: Human Machine Interfaces
Classifier: Topic :: Scientific/Engineering :: Visualization
Classifier: License :: OSI Approved :: MIT License
Classifier: Operating System :: OS Independent
Classifier: Topic :: Software Development :: Libraries :: Python Modules
Classifier: Topic :: Software Development :: User Interfaces
License-File: LICENSE
Requires-Dist: toml
